<?xml version="1.0" encoding="UTF-8"?>
<jappix xmlns="jappix:api:version">
	<id>Spaco [0.9]</id>
	<url>http://download.jappix.org/jappixorg/jappix-0.9-spaco.tar.bz2</url>
	<url2>http://download.jappix.org/jappixorg/jappix-0.9-spaco.zip</url2>
	<description>Jappix Spaco is the most advanced XMPP web-client in the world! Furthermore, it is a complete distributed social platform.\n\nThis new version provides lots of bugfixes.\n\n
	</description>
	<next>0.9.1</next>
	<further>0.9.2</further>
</jappix>
